README.md
setup.cfg
setup.py
gym_wumpus/__init__.py
gym_wumpus.egg-info/PKG-INFO
gym_wumpus.egg-info/SOURCES.txt
gym_wumpus.egg-info/dependency_links.txt
gym_wumpus.egg-info/requires.txt
gym_wumpus.egg-info/top_level.txt