Metadata-Version: 1.1
Name: gym-wumpus
Version: 0.1.1
Summary: Wumpus World environment for gym
Home-page: https://github.com/Davood-M/gym_wumpus_world
Author: David Mosallanezhad
Author-email: amosalla@asu.edu
License: MIT
Download-URL: https://github.com/Davood-M/gym_wumpus_world/archive/0.1.1.tar.gz
Keywords: wumpus world,wumpus,gym
Platform: UNKNOWN
Classifier: Development Status :: 3 - Alpha
Classifier: Intended Audience :: Developers
Classifier: Topic :: Software Development :: Build Tools
Classifier: License :: OSI Approved :: MIT License
Classifier: Programming Language :: Python :: 3
Classifier: Programming Language :: Python :: 3.4
Classifier: Programming Language :: Python :: 3.5
Classifier: Programming Language :: Python :: 3.6
Classifier: Programming Language :: Python :: 3.7
